docs/source/conf.py
iothealth/__init__.py
iothealth/__main__.py
iothealth/_base_health.py
iothealth/device_health.py
iothealth/linux.py
iothealth/raspberry_pi.py
iothealth/bin/__init__.py
iothealth/bin/cli.py
iothealth-0.0.6.dist-info/LICENSE
iothealth-0.0.6.dist-info/METADATA
iothealth-0.0.6.dist-info/WHEEL
iothealth-0.0.6.dist-info/entry_points.txt
iothealth-0.0.6.dist-info/top_level.txt
iothealth-0.0.6.dist-info/RECORD
