Metadata-Version: 2.1
Name: iothealth
Version: 0.0.6
Summary: Health and Status Library for IoT Devices
Author: IoT Spectator
License: MIT License
Project-URL: repository, https://github.com/iot-spectator/iot-health
Keywords: IoT
Classifier: License :: OSI Approved :: MIT License
Classifier: Programming Language :: Python
Requires-Python: >=3.9
License-File: LICENSE
Requires-Dist: click
Requires-Dist: psutil
